manticore/__init__.py
manticore/routers.py
manticore/backend/__init__.py
manticore/backend/base.py
manticore/backend/compiler.py
manticore/backend/schema.py
manticore/models/__init__.py
manticore/models/base.py
manticore/models/fields.py
manticore/models/functions.py
manticore/models/lookups.py
manticore/models/manager.py
manticore/models/query.py
manticore/models/sql/__init__.py
manticore/models/sql/compiler.py
manticore/models/sql/query.py
manticore/models/sql/where.py
manticore/sphinxql/__init__.py
manticore/sphinxql/base.py
manticore/sphinxql/expressions.py
django_manticore-0.2.0.dist-info/METADATA
django_manticore-0.2.0.dist-info/WHEEL
django_manticore-0.2.0.dist-info/top_level.txt
django_manticore-0.2.0.dist-info/RECORD
